{"@type":"Flow","@id":"c1339a34-352c-3152-9043-ee513a5f7c3a","name":"Octylphenol","description":"From Federal Elementary Flow List v1.3.0, written by fedelemflowlist v1.3.0. Flow Class: Chemicals. Not a preferred flow.","category":"Elementary flows/emission/ground","version":"01.03.000","lastChange":"2024-12-17T05:39:11.953Z","flowType":"ELEMENTARY_FLOW","cas":"67554-50-1","formula":"-","synonyms":"Phenol, octyl-","isInfrastructureFlow":false,"flowProperties":[{"@type":"FlowPropertyFactor","isRefFlowProperty":true,"flowProperty":{"@type":"FlowProperty","@id":"93a60a56-a3c8-11da-a746-0800200b9a66","name":"Mass","category":"Technical flow properties","refUnit":"kg"},"conversionFactor":1.0}]}