{"@type":"Flow","@id":"fc58ffbc-611b-32e7-8f39-05c03adca463","name":"Estrone","description":"From Federal Elementary Flow List v1.3.0, written by fedelemflowlist v1.3.0. Flow Class: Chemicals. Not a preferred flow.","category":"Elementary flows/emission/ground","version":"01.03.000","lastChange":"2024-12-17T05:38:47.355Z","flowType":"ELEMENTARY_FLOW","cas":"53-16-7","formula":"C18H22O2","synonyms":"Estra-1,3,5(10)-trien-17-one, 3-hydroxy-","isInfrastructureFlow":false,"flowProperties":[{"@type":"FlowPropertyFactor","isRefFlowProperty":true,"flowProperty":{"@type":"FlowProperty","@id":"93a60a56-a3c8-11da-a746-0800200b9a66","name":"Mass","category":"Technical flow properties","refUnit":"kg"},"conversionFactor":1.0}]}